peak/__init__.py
peak/__main__.py
peak/bootloader.py
peak/core.py
peak/logging.py
peak/main.py
peak/message.py
peak/template.py
peak/agents/__init__.py
peak/agents/directory_facilitator/df.py
peak/agents/directory_facilitator/behaviors/__init__.py
peak/agents/directory_facilitator/behaviors/create_graph.py
peak/agents/directory_facilitator/behaviors/ecosystem_hierarchy.py
peak/agents/directory_facilitator/behaviors/search_community.py
peak/agents/dummy_agent/dummy_agent.py
peak/agents/dummy_agent/behaviors/__init__.py
peak/agents/dummy_agent/behaviors/send_message.py
peak/agents/sync_agent/sync_agent.py
peak/agents/sync_agent/behaviors/__init__.py
peak/agents/sync_agent/behaviors/step.py
peak/agents/synchronizer/synchronizer.py
peak/agents/synchronizer/behaviors/__init__.py
peak/agents/synchronizer/behaviors/datetime_clock.py
peak/agents/synchronizer/behaviors/periodic_clock.py
peak/behaviours/__init__.py
peak/behaviours/create_graph.py
peak/behaviours/join_community.py
peak/behaviours/leave_community.py
peak/behaviours/search_community.py
peak/cli/__init__.py
peak/cli/df.py
peak/cli/run.py
peak/cli/send.py
peak/cli/start.py
peak_mas-1.2.8.dist-info/licenses/LICENSE
peak_mas-1.2.8.dist-info/METADATA
peak_mas-1.2.8.dist-info/WHEEL
peak_mas-1.2.8.dist-info/entry_points.txt
peak_mas-1.2.8.dist-info/top_level.txt
peak_mas-1.2.8.dist-info/RECORD
