Metadata-Version: 2.4
Name: peak-mas
Version: 1.2.8
Summary: Python-based framework for heterogeneous agent communities
Author-email: Bruno Ribeiro <brgri@isep.ipp.pt>, Luis Gomes <log@isep.ipp.pt>
Project-URL: Homepage, https://www.gecad.isep.ipp.pt/peak
Project-URL: Github, https://github.com/gecad-group/peak-mas
Keywords: framework,multiagent,agent-based,ecosystem,spade,xmpp
Classifier: License :: OSI Approved :: GNU General Public License v3 (GPLv3)
Classifier: Programming Language :: Python
Classifier: Programming Language :: Python :: 3
Classifier: Programming Language :: Python :: 3.9
Classifier: Environment :: Console
Classifier: Operating System :: Microsoft :: Windows
Classifier: Operating System :: POSIX :: Linux
Classifier: Topic :: Scientific/Engineering
Classifier: Topic :: Scientific/Engineering :: Artificial Intelligence
Requires-Python: ==3.9.6
License-File: LICENSE
Requires-Dist: aiohttp_cors
Requires-Dist: aioxmpp
Requires-Dist: pandas
Requires-Dist: spade==3.2.2
Requires-Dist: PyYAML
Provides-Extra: build
Requires-Dist: build; extra == "build"
Requires-Dist: twine; extra == "build"
Requires-Dist: pyotp; extra == "build"
Provides-Extra: dev
Requires-Dist: black; extra == "dev"
Requires-Dist: isort; extra == "dev"
Requires-Dist: mypy; extra == "dev"
Requires-Dist: bumpver; extra == "dev"
Requires-Dist: pipreqs; extra == "dev"
Requires-Dist: autoflake; extra == "dev"
Requires-Dist: pylint; extra == "dev"
Dynamic: license-file
